asyncpipe.py
asyncpipe-0.0.1.dist-info/LICENSE.md
asyncpipe-0.0.1.dist-info/METADATA
asyncpipe-0.0.1.dist-info/WHEEL
asyncpipe-0.0.1.dist-info/top_level.txt
asyncpipe-0.0.1.dist-info/RECORD
