Metadata-Version: 2.1
Name: asyncpipe
Version: 0.0.1
Summary: An async-compatible library for composing Python shell pipelines
Home-page: https://github.com/beckjake/asyncpipe
Author: Jacob Beck
Author-email: pypi@jacob.ebeck.io
License: MIT
Platform: UNKNOWN
Classifier: Programming Language :: Python :: 3.5
Classifier: Programming Language :: Python :: 3.6
Classifier: Programming Language :: Python :: 3.7
Classifier: License :: OSI Approved :: MIT License
Classifier: Operating System :: POSIX
Requires-Python: ~=3.5
